<?xml version="1.0" encoding="UTF-8" ?>
<!DOCTYPE mapper PUBLIC "-//mybatis.org//DTD Mapper 3.0//EN"
        "http://mybatis.org/dtd/mybatis-3-mapper.dtd">

<mapper namespace="erp.report.stock.movement.mapper.StockMovementMapper">

    <!-- 상단 요약 -->
    <select id="findMovementSummary" resultType="StockMovementSummaryRow">
        SELECT
        (SELECT NVL(SUM(s.on_hand_quantity), 0)
        FROM item i
        JOIN stock s ON s.item_id = i.item_id
        WHERE i.item_id = #{filter.itemId}
        AND i.deleted_at IS NULL
        AND
        <include refid="frag.tenantGuardAlias">
            <property name="alias" value="i"/>
        </include>
        AND
        <include refid="frag.tenantGuardAlias">
            <property name="alias" value="s"/>
        </include>
        ) AS onHandQuantity,

        (SELECT s.warehouse
        FROM stock s
        JOIN item i2 ON i2.item_id = s.item_id
        WHERE i2.item_id = #{filter.itemId}
        AND i2.deleted_at IS NULL
        AND
        <include refid="frag.tenantGuardAlias">
            <property name="alias" value="i2"/>
        </include>
        AND
        <include refid="frag.tenantGuardAlias">
            <property name="alias" value="s"/>
        </include>
        ) AS warehouse,

        (SELECT COUNT(DISTINCT inb.inbound_id)
        FROM inbound inb
        JOIN purchase p ON p.purchase_id = inb.purchase_id
        JOIN purchase_item pi ON pi.purchase_id = p.purchase_id
        JOIN item i ON i.item_id = pi.item_id
        WHERE i.item_id = #{filter.itemId}
        <if test="filter.startDate != null">AND inb.inbound_date &gt;=
            #{filter.startDate}
        </if>
        <if test="filter.endDate != null">AND inb.inbound_date &lt;=
            #{filter.endDate}
        </if>
        <if test="filter.code != null">AND UPPER(inb.code) LIKE '%' ||
            UPPER(#{filter.code}) || '%'
        </if>
        <choose>
            <when test="filter.status != null and filter.status.name() == 'ACTIVE'">
                AND inb.status = 'ACTIVE'
            </when>
            <when test="filter.status != null and filter.status.name() == 'CANCELED'">
                AND inb.status = 'CANCELED'
            </when>
        </choose>
        AND i.deleted_at IS NULL
        AND
        <include refid="frag.tenantGuardAlias">
            <property name="alias" value="i"/>
        </include>
        AND
        <include refid="frag.tenantGuardAlias">
            <property name="alias" value="inb"/>
        </include>
        AND
        <include refid="frag.tenantGuardAlias">
            <property name="alias" value="p"/>
        </include>
        ) AS totalInboundCount,

        (SELECT COUNT(DISTINCT outb.outbound_id)
        FROM outbound outb
        JOIN orders o ON o.order_id = outb.order_id
        JOIN order_item oi ON oi.order_id = o.order_id
        JOIN item i ON i.item_id = oi.item_id
        WHERE i.item_id = #{filter.itemId}
        <if test="filter.startDate != null">AND outb.outbound_date &gt;=
            #{filter.startDate}
        </if>
        <if test="filter.endDate != null">AND outb.outbound_date &lt;=
            #{filter.endDate}
        </if>
        <if test="filter.code != null">AND UPPER(outb.code) LIKE '%' ||
            UPPER(#{filter.code}) || '%'
        </if>
        <choose>
            <when test="filter.status != null and filter.status.name() == 'ACTIVE'">
                AND outb.status = 'ACTIVE'
            </when>
            <when test="filter.status != null and filter.status.name() == 'CANCELED'">
                AND outb.status = 'CANCELED'
            </when>
        </choose>
        AND i.deleted_at IS NULL
        AND
        <include refid="frag.tenantGuardAlias">
            <property name="alias" value="i"/>
        </include>
        AND
        <include refid="frag.tenantGuardAlias">
            <property name="alias" value="outb"/>
        </include>
        AND
        <include refid="frag.tenantGuardAlias">
            <property name="alias" value="o"/>
        </include>
        ) AS totalOutboundCount
        FROM dual
    </select>

    <!-- 상세 변동 목록 -->
    <select id="findMovementRows" resultType="StockMovementFindRow">
        SELECT *
        FROM (
        SELECT
        inb.inbound_date AS movementDate,
        'INBOUND' AS movementType,
        SUM(pi.quantity) AS quantity,
        e.name AS employeeName,
        inb.code AS code,
        inb.status AS status,
        s.warehouse AS warehouse
        FROM inbound inb
        JOIN purchase p ON p.purchase_id = inb.purchase_id
        JOIN purchase_item pi ON pi.purchase_id = p.purchase_id
        JOIN item i ON i.item_id = pi.item_id
        JOIN stock s ON s.item_id = i.item_id
        JOIN employee e ON e.employee_id = inb.employee_id
        WHERE i.item_id = #{filter.itemId}
        <if test="filter.startDate != null">AND inb.inbound_date &gt;=
            #{filter.startDate}
        </if>
        <if test="filter.endDate != null">AND inb.inbound_date &lt;=
            #{filter.endDate}
        </if>
        <if test="filter.code != null">AND UPPER(inb.code) LIKE '%' ||
            UPPER(#{filter.code}) || '%'
        </if>
        <choose>
            <when test="filter.status != null and filter.status.name() == 'ACTIVE'">
                AND inb.status = 'ACTIVE'
            </when>
            <when test="filter.status != null and filter.status.name() == 'CANCELED'">
                AND inb.status = 'CANCELED'
            </when>
        </choose>
        AND i.deleted_at IS NULL
        AND
        <include refid="frag.tenantGuardAlias">
            <property name="alias" value="i"/>
        </include>
        AND
        <include refid="frag.tenantGuardAlias">
            <property name="alias" value="inb"/>
        </include>
        AND
        <include refid="frag.tenantGuardAlias">
            <property name="alias" value="p"/>
        </include>
        AND
        <include refid="frag.tenantGuardAlias">
            <property name="alias" value="s"/>
        </include>
        AND
        <include refid="frag.tenantGuardAlias">
            <property name="alias" value="e"/>
        </include>
        GROUP BY inb.inbound_date, e.name, inb.code, inb.status, s.warehouse

        UNION ALL

        SELECT
        outb.outbound_date AS movementDate,
        'OUTBOUND' AS movementType,
        SUM(oi.quantity) AS quantity,
        e.name AS employeeName,
        outb.code AS code,
        outb.status AS status,
        s.warehouse AS warehouse
        FROM outbound outb
        JOIN orders o ON o.order_id = outb.order_id
        JOIN order_item oi ON oi.order_id = o.order_id
        JOIN item i ON i.item_id = oi.item_id
        JOIN stock s ON s.item_id = i.item_id
        JOIN employee e ON e.employee_id = outb.employee_id
        WHERE i.item_id = #{filter.itemId}
        <if test="filter.startDate != null">AND outb.outbound_date &gt;=
            #{filter.startDate}
        </if>
        <if test="filter.endDate != null">AND outb.outbound_date &lt;=
            #{filter.endDate}
        </if>
        <if test="filter.code != null">AND UPPER(outb.code) LIKE '%' ||
            UPPER(#{filter.code}) || '%'
        </if>
        <choose>
            <when test="filter.status != null and filter.status.name() == 'ACTIVE'">
                AND outb.status = 'ACTIVE'
            </when>
            <when test="filter.status != null and filter.status.name() == 'CANCELED'">
                AND outb.status = 'CANCELED'
            </when>
        </choose>
        AND i.deleted_at IS NULL
        AND
        <include refid="frag.tenantGuardAlias">
            <property name="alias" value="i"/>
        </include>
        AND
        <include refid="frag.tenantGuardAlias">
            <property name="alias" value="outb"/>
        </include>
        AND
        <include refid="frag.tenantGuardAlias">
            <property name="alias" value="o"/>
        </include>
        AND
        <include refid="frag.tenantGuardAlias">
            <property name="alias" value="s"/>
        </include>
        AND
        <include refid="frag.tenantGuardAlias">
            <property name="alias" value="e"/>
        </include>
        GROUP BY outb.outbound_date, e.name, outb.code, outb.status, s.warehouse
        )
        ORDER BY movementDate DESC, code DESC
        OFFSET #{filter.offset} ROWS FETCH NEXT #{filter.size} ROWS ONLY
    </select>

    <!-- 총 개수 -->
    <select id="countMovementRows" resultType="long">
        SELECT COUNT(1) FROM (
        SELECT inb.inbound_id AS id
        FROM inbound inb
        JOIN purchase p ON p.purchase_id = inb.purchase_id
        JOIN purchase_item pi ON pi.purchase_id = p.purchase_id
        JOIN item i ON i.item_id = pi.item_id
        WHERE i.item_id = #{filter.itemId}
        <if test="filter.startDate != null">AND inb.inbound_date &gt;=
            #{filter.startDate}
        </if>
        <if test="filter.endDate != null">AND inb.inbound_date &lt;=
            #{filter.endDate}
        </if>
        <if test="filter.code != null">AND UPPER(inb.code) LIKE '%' ||
            UPPER(#{filter.code}) || '%'
        </if>
        <choose>
            <when test="filter.status != null and filter.status.name() == 'ACTIVE'">
                AND inb.status = 'ACTIVE'
            </when>
            <when test="filter.status != null and filter.status.name() == 'CANCELED'">
                AND inb.status = 'CANCELED'
            </when>
        </choose>
        AND i.deleted_at IS NULL
        AND
        <include refid="frag.tenantGuardAlias">
            <property name="alias" value="i"/>
        </include>
        AND
        <include refid="frag.tenantGuardAlias">
            <property name="alias" value="inb"/>
        </include>
        AND
        <include refid="frag.tenantGuardAlias">
            <property name="alias" value="p"/>
        </include>

        UNION ALL

        SELECT outb.outbound_id AS id
        FROM outbound outb
        JOIN orders o ON o.order_id = outb.order_id
        JOIN order_item oi ON oi.order_id = o.order_id
        JOIN item i ON i.item_id = oi.item_id
        WHERE i.item_id = #{filter.itemId}
        <if test="filter.startDate != null">AND outb.outbound_date &gt;=
            #{filter.startDate}
        </if>
        <if test="filter.endDate != null">AND outb.outbound_date &lt;=
            #{filter.endDate}
        </if>
        <if test="filter.code != null">AND UPPER(outb.code) LIKE '%' ||
            UPPER(#{filter.code}) || '%'
        </if>
        <choose>
            <when test="filter.status != null and filter.status.name() == 'ACTIVE'">
                AND outb.status = 'ACTIVE'
            </when>
            <when test="filter.status != null and filter.status.name() == 'CANCELED'">
                AND outb.status = 'CANCELED'
            </when>
        </choose>
        AND i.deleted_at IS NULL
        AND
        <include refid="frag.tenantGuardAlias">
            <property name="alias" value="i"/>
        </include>
        AND
        <include refid="frag.tenantGuardAlias">
            <property name="alias" value="outb"/>
        </include>
        AND
        <include refid="frag.tenantGuardAlias">
            <property name="alias" value="o"/>
        </include>
        )
    </select>

</mapper>
